csf/__init__.py
csf/ranch/__init__.py
csf/ranch/__version__.py
csf/ranch/admin.py
csf/ranch/apps.py
csf/ranch/constants.py
csf/ranch/controllers.py
csf/ranch/exceptions.py
csf/ranch/models.py
csf/ranch/lib/__init__.py
csf/ranch/lib/error_handling.py
csf/ranch/management/__init__.py
csf/ranch/management/commands/__init__.py
csf/ranch/management/commands/delete_failed_tasks.py
csf/ranch/management/commands/rerun_logged_tasks.py
csf/ranch/migrations/0001_initial.py
csf/ranch/migrations/0002_loggedtask_queue.py
csf/ranch/migrations/__init__.py
csf/ranch/signal_handlers/__init__.py
csf/ranch/signal_handlers/metrics_handlers.py
csf/ranch/signal_handlers/persistence_handlers.py
csf/ranch/tests/__init__.py
csf/ranch/tests/test_controllers.py
csf_ranch-1.2.2.dist-info/METADATA
csf_ranch-1.2.2.dist-info/WHEEL
csf_ranch-1.2.2.dist-info/top_level.txt
csf_ranch-1.2.2.dist-info/RECORD
